target_py/__init__.py
target_py/__main__.py
target_py/example/__init__.py
target_py/example/generate.py
target_py/example/data/25m-no_grid_lc.csv
target_py/example/data/30m_grid_lc.csv
target_py/example/data/30min_no_grid_met.csv
target_py/example/data/30min_no_grid_obs.csv
target_py/example/data/stations_LST.zip
target_py/scripts/CD.py
target_py/scripts/Httc.py
target_py/scripts/LUMPS.py
target_py/scripts/LcSort.py
target_py/scripts/SfcRi.py
target_py/scripts/Ta_module_new.py
target_py/scripts/TbRurSolver.py
target_py/scripts/UTCI.py
target_py/scripts/__init__.py
target_py/scripts/force_restore.py
target_py/scripts/ld_mod.py
target_py/scripts/plotting.py
target_py/scripts/rn_calc.py
target_py/scripts/simple_water.py
target_py/scripts/toolkit.py
target_py/ui/__init__.py
target_py/ui/argparse.py
target_py/ui/logger.py
target_py/ui/utils.py
target_py-0.1.1.dist-info/METADATA
target_py-0.1.1.dist-info/WHEEL
target_py-0.1.1.dist-info/top_level.txt
target_py-0.1.1.dist-info/RECORD
