Metadata-Version: 2.1
Name: target-py
Version: 0.1.1
Summary: Python version of the air temperature response to green/blue infrastructure evaluation tool (TARGET)
Home-page: https://github.com/jixuan-chen/target
Author: Jixuan Chen
Author-email: jixuan.chen@eawag.ch
License: UNKNOWN
Platform: UNKNOWN
Requires-Python: >=3.8
Requires-Dist: matplotlib>=3.5.0
Requires-Dist: numpy>=1.24.4
Requires-Dist: pandas>=2.0.3
Requires-Dist: scipy>=1.10.1
Requires-Dist: setuptools>=75.1.0
Requires-Dist: tqdm>=4.54.1
